pytka/__init__.py
pytka-0.0.0.dist-info/LICENSE
pytka-0.0.0.dist-info/METADATA
pytka-0.0.0.dist-info/WHEEL
pytka-0.0.0.dist-info/top_level.txt
pytka-0.0.0.dist-info/RECORD
