Metadata-Version: 2.1
Name: pytka
Version: 0.0.0
Summary: Simple pytka.
Author-email: myslak71 <myslak@protonmail.com>
Maintainer-email: myslak71 <myslak@protonmail.com>
License: MIT License
Project-URL: repository, https://github.com/myslak71/pytka
Keywords: pytka
Classifier: Development Status :: 3 - Alpha
Classifier: License :: OSI Approved :: MIT License
Classifier: Operating System :: OS Independent
Classifier: Programming Language :: Python
Classifier: Programming Language :: Python :: 3.11
Classifier: Programming Language :: Python :: 3 :: Only
Requires-Python: >=3.11
License-File: LICENSE
